dj_nexmo-0.0.4.dist-info/METADATA
dj_nexmo-0.0.4.dist-info/RECORD
dj_nexmo-0.0.4.dist-info/WHEEL
dj_nexmo-0.0.4.dist-info/entry_points.txt
dj_nexmo-0.0.4.dist-info/pbr.json
dj_nexmo-0.0.4.dist-info/top_level.txt
dj_nexmo-0.0.4.dist-info/zip-safe
djnexmo/__init__.py
djnexmo/admin.py
djnexmo/apps.py
djnexmo/decorators.py
djnexmo/models.py
djnexmo/views.py
djnexmo/migrations/0001_initial.py
djnexmo/migrations/0002_auto_20180426_1521.py
djnexmo/migrations/0003_auto_20180426_1802.py
djnexmo/migrations/0004_auto_20180427_1517.py
djnexmo/migrations/0005_auto_20180430_1523.py
djnexmo/migrations/__init__.py
djnexmo/templatetags/__init__.py
djnexmo/templatetags/phonenumbers.py
