Metadata-Version: 2.1
Name: dj-nexmo
Version: 0.0.4
Summary: Utilities for Django developers using Nexmo's APIs
Home-page: https://github.com/Nexmo/dj-nexmo/
Author: Nexmo Developer Relations
Author-email: devrel@nexmo.com
License: UNKNOWN
Platform: UNKNOWN
Classifier: Development Status :: 4 - Beta
Classifier: Framework :: Django :: 2.0
Classifier: Framework :: Django :: 2.1
Classifier: Intended Audience :: Developers
Classifier: License :: OSI Approved :: Apache Software License
Classifier: Operating System :: OS Independent
Classifier: Programming Language :: Python :: 3
Classifier: Programming Language :: Python :: 3.5
Classifier: Programming Language :: Python :: 3.6
Classifier: Programming Language :: Python :: 3 :: Only
Classifier: Topic :: Communications :: Telephony
Requires-Python: >=3.4
Requires-Dist: nexmo (~=2.0)
Requires-Dist: django (~=2.0)
Requires-Dist: attrs (~=17.4)
Requires-Dist: marshmallow (>=3.0.0rc3)
Requires-Dist: phonenumbers (~=8.9)
